pywst/__init__.py
pywst/filters.py
pywst/rwst.py
pywst/rwst_models.py
pywst/rwst_operator.py
pywst/utils.py
pywst/wst.py
pywst/wst_operator.py
pywst-1.0.dist-info/LICENSE.md
pywst-1.0.dist-info/METADATA
pywst-1.0.dist-info/WHEEL
pywst-1.0.dist-info/top_level.txt
pywst-1.0.dist-info/RECORD
