Metadata-Version: 2.1
Name: pywst
Version: 1.0
Summary: WST and RWST analyses tools for astrophysical data.
Home-page: https://github.com/bregaldo/pywst
Author: Bruno Régaldo-Saint Blancard
Author-email: bruno.regaldo@phys.ens.fr
Classifier: Programming Language :: Python :: 3
Classifier: License :: OSI Approved :: BSD License
Classifier: Operating System :: OS Independent
Requires-Python: >=3.6
License-File: LICENSE.md
